{
	"name": "SnowflakeTable_Dim_Person",
	"properties": {
		"linkedServiceName": {
			"referenceName": "SnowflakeLSIMDB",
			"type": "LinkedServiceReference"
		},
		"annotations": [],
		"type": "SnowflakeV2Table",
		"schema": [
			{
				"name": "PERSON_ID_SK",
				"type": "NUMBER",
				"precision": 38,
				"scale": 0
			},
			{
				"name": "NCONST",
				"type": "VARCHAR"
			},
			{
				"name": "PRIMARY_NAME",
				"type": "VARCHAR"
			},
			{
				"name": "BIRTH_YEAR",
				"type": "NUMBER",
				"precision": 38,
				"scale": 0
			},
			{
				"name": "DEATH_YEAR",
				"type": "NUMBER",
				"precision": 38,
				"scale": 0
			},
			{
				"name": "JOB_ID",
				"type": "VARCHAR"
			},
			{
				"name": "LOAD_DT",
				"type": "DATE"
			}
		],
		"typeProperties": {
			"schema": "IMDB_SCHEMA",
			"table": "DIM_PERSON"
		}
	}
}